meshtaichi_patcher_core.cpython-38-darwin.so
meshtaichi_patcher/__init__.py
meshtaichi_patcher/cluster.py
meshtaichi_patcher/meshpatcher.py
meshtaichi_patcher/relation.py
meshtaichi_patcher-0.0.19.dist-info/LICENSE
meshtaichi_patcher-0.0.19.dist-info/METADATA
meshtaichi_patcher-0.0.19.dist-info/WHEEL
meshtaichi_patcher-0.0.19.dist-info/top_level.txt
meshtaichi_patcher-0.0.19.dist-info/RECORD
