Metadata-Version: 2.1
Name: meshtaichi_patcher
Version: 0.0.19
Summary: a mesh patcher for meshtaichi
Author-email: BillXu2000 <BillXu2000@126.com>
Project-URL: Homepage, https://github.com/BillXu2000/meshtaichi_patcher
Requires-Python: >=3.6
License-File: LICENSE
